tryton/__init__.py
tryton/bus.py
tryton/cache.py
tryton/chat.py
tryton/client.py
tryton/config.py
tryton/device_cookie.py
tryton/exceptions.py
tryton/fingerprints.py
tryton/jsonrpc.py
tryton/pyson.py
tryton/rpc.py
tryton/translate.py
tryton/action/__init__.py
tryton/action/main.py
tryton/common/__init__.py
tryton/common/button.py
tryton/common/cellrendererbinary.py
tryton/common/cellrendererbutton.py
tryton/common/cellrendererclickablepixbuf.py
tryton/common/cellrenderercombo.py
tryton/common/cellrendererfloat.py
tryton/common/cellrendererinteger.py
tryton/common/cellrenderertext.py
tryton/common/cellrenderertoggle.py
tryton/common/common.py
tryton/common/completion.py
tryton/common/datetime_.py
tryton/common/domain_inversion.py
tryton/common/domain_parser.py
tryton/common/entry_position.py
tryton/common/environment.py
tryton/common/focus.py
tryton/common/htmltextbuffer.py
tryton/common/number_entry.py
tryton/common/popup_menu.py
tryton/common/richtext.py
tryton/common/selection.py
tryton/common/tempfile.py
tryton/common/timedelta.py
tryton/common/underline.py
tryton/common/widget_style.py
tryton/data/locale/bg/LC_MESSAGES/tryton.mo
tryton/data/locale/bg/LC_MESSAGES/tryton.po
tryton/data/locale/ca/LC_MESSAGES/tryton.mo
tryton/data/locale/ca/LC_MESSAGES/tryton.po
tryton/data/locale/cs/LC_MESSAGES/tryton.mo
tryton/data/locale/cs/LC_MESSAGES/tryton.po
tryton/data/locale/de/LC_MESSAGES/tryton.mo
tryton/data/locale/de/LC_MESSAGES/tryton.po
tryton/data/locale/es/LC_MESSAGES/tryton.mo
tryton/data/locale/es/LC_MESSAGES/tryton.po
tryton/data/locale/es_419/LC_MESSAGES/tryton.mo
tryton/data/locale/es_419/LC_MESSAGES/tryton.po
tryton/data/locale/et/LC_MESSAGES/tryton.mo
tryton/data/locale/et/LC_MESSAGES/tryton.po
tryton/data/locale/fa/LC_MESSAGES/tryton.mo
tryton/data/locale/fa/LC_MESSAGES/tryton.po
tryton/data/locale/fi/LC_MESSAGES/tryton.mo
tryton/data/locale/fi/LC_MESSAGES/tryton.po
tryton/data/locale/fr/LC_MESSAGES/tryton.mo
tryton/data/locale/fr/LC_MESSAGES/tryton.po
tryton-7.8.2.dist-info/licenses/LICENSE
tryton-7.8.2.dist-info/METADATA
tryton-7.8.2.dist-info/WHEEL
tryton-7.8.2.dist-info/top_level.txt
tryton-7.8.2.dist-info/RECORD
